setup.cfg
setup.py
gexdat/__init__.py
gexdat/gexdat.py
gexdat.egg-info/PKG-INFO
gexdat.egg-info/SOURCES.txt
gexdat.egg-info/dependency_links.txt
gexdat.egg-info/top_level.txt