Metadata-Version: 1.1
Name: gexdat
Version: 0.2
Summary: An easy way to write gephi style gexf graph files
Home-page: https://github.com/PorkShoulderHolder/gexdat
Author: Sam Royston
Author-email: sfoxroyston@gmail.com
License: MIT
Download-URL: https://github.com/PorkShoulderHolder/gexdat/tarball/0.2
Keywords: gexdat
Platform: UNKNOWN
Classifier: Topic :: Utilities
